modeldb/__init__.py
modeldb/__main__.py
modeldb/syncer.json
modeldb/basic/ModelDbSyncerBase.py
modeldb/basic/Structs.py
modeldb/basic/__init__.py
modeldb/events/Event.py
modeldb/events/ExperimentEvent.py
modeldb/events/ExperimentRunEvent.py
modeldb/events/FitEvent.py
modeldb/events/GridSearchCVEvent.py
modeldb/events/MetricEvent.py
modeldb/events/PipelineEvent.py
modeldb/events/ProjectEvent.py
modeldb/events/RandomSplitEvent.py
modeldb/events/TransformEvent.py
modeldb/events/__init__.py
modeldb/thrift/__init__.py
modeldb/thrift/modeldb/ModelDBService.py
modeldb/thrift/modeldb/__init__.py
modeldb/thrift/modeldb/constants.py
modeldb/thrift/modeldb/ttypes.py
modeldb/utils/ConfigUtils.py
modeldb/utils/MetadataConstants.py
modeldb/utils/__init__.py
modeldb_basic-0.1.35.dist-info/DESCRIPTION.rst
modeldb_basic-0.1.35.dist-info/METADATA
modeldb_basic-0.1.35.dist-info/RECORD
modeldb_basic-0.1.35.dist-info/WHEEL
modeldb_basic-0.1.35.dist-info/entry_points.txt
modeldb_basic-0.1.35.dist-info/metadata.json
modeldb_basic-0.1.35.dist-info/top_level.txt
