Metadata-Version: 2.0
Name: modeldb-basic
Version: 0.1.35
Summary: A system to manage machine learning models
Home-page: https://github.com/engapa/modeldb-basic/tree/master
Author: UNKNOWN
Author-email: UNKNOWN
License: MIT
Keywords: Machine Learning ML model catalog
Platform: UNKNOWN
Classifier: Development Status :: 3 - Alpha
Classifier: Intended Audience :: Developers
Classifier: Intended Audience :: Science/Research
Classifier: Topic :: Scientific/Engineering
Classifier: License :: OSI Approved :: MIT License
Classifier: Programming Language :: Python :: 2.7
Classifier: Programming Language :: Python :: 3.5
Classifier: Programming Language :: Python :: 3.6
Requires-Dist: thrift
Requires-Dist: pyyaml
Requires-Dist: requests
Requires-Dist: dpath
